apipipeline/__init__.py
apipipeline/api_request_pipeline.py
apipipeline-0.0.2.dist-info/LICENSE
apipipeline-0.0.2.dist-info/METADATA
apipipeline-0.0.2.dist-info/WHEEL
apipipeline-0.0.2.dist-info/top_level.txt
apipipeline-0.0.2.dist-info/RECORD
